MANIFEST.in
README.md
setup.py
archive/__init__.py
archive/delineation.py
archive/distributions.py
archive/iterators.py
archive/maths.py
archive/networks.py
archive/old_analysis.py
archive/old_controllers.py
archive/old_models.py
archive/old_network.py
archive/old_views.py
archive/rational.py
archive/render.py
archive/tables.py
archive/test_speed.py
archive/writer_old.py
archive/app/__init__.py
archive/app/main.py
archive/app/system.py
archive/app/controllers/__init__.py
archive/app/controllers/controllers.py
archive/app/models/__init__.py
archive/app/models/databases.py
archive/app/models/models.py
archive/app/models/write.py
archive/app/tests/__init__.py
archive/app/tests/test_models.py
archive/app/views/__init__.py
archive/app/views/render.py
archive/app/views/views.py
archive/app/views/widgets.py
archive/hydrology/__init__.py
archive/hydrology/rational.py
archive/hydrology/scs.py
pyflo/__init__.py
pyflo/basins.py
pyflo/build.py
pyflo/constants.py
pyflo/distributions.py
pyflo/links.py
pyflo/networks.py
pyflo/routing.py
pyflo/sections.py
pyflo/system.py
pyflo/terrain.py
pyflo.egg-info/PKG-INFO
pyflo.egg-info/SOURCES.txt
pyflo.egg-info/dependency_links.txt
pyflo.egg-info/requires.txt
pyflo.egg-info/top_level.txt
pyflo/nrcs/__init__.py
pyflo/nrcs/hydrology.py
pyflo/rational/__init__.py
pyflo/rational/hydraulics.py
pyflo/rational/hydrology.py
requirements/production.txt
site/__init__.py