Metadata-Version: 1.1
Name: pyflo
Version: 0.3.3
Summary: PyFlo is an open-source library written in Python for performing hydraulic and hydrology stormwater analysis. 
Home-page: https://benjiyamin.github.io/pyflo
Author: benjiyamin, see AUTHORS.md
Author-email: benjiyamin@gmail.com
License: GNU General Public License v3 (GPLv3), see LICENSE.md
Keywords: hydraulics hydrology storm simulation
Platform: UNKNOWN
Classifier: Development Status :: 4 - Beta
Classifier: Operating System :: MacOS :: MacOS X
Classifier: Operating System :: Microsoft :: Windows
Classifier: Operating System :: POSIX
Classifier: License :: OSI Approved :: GNU General Public License v3 (GPLv3)
Classifier: Programming Language :: Python
